setup.py
aio_periodic_task/__init__.py
aio_periodic_task/periodic_task.py
aio_periodic_task.egg-info/PKG-INFO
aio_periodic_task.egg-info/SOURCES.txt
aio_periodic_task.egg-info/dependency_links.txt
aio_periodic_task.egg-info/top_level.txt