Metadata-Version: 1.1
Name: aio-periodic-task
Version: 0.1.1
Summary: periodic task for asyncio
Home-page: https://github.com/shicky/aio_periodic_task
Author: Sick Yoon
Author-email: shicky@gmail.com
License: MIT
Keywords: asyncio,aio-libs,aiohttp
Platform: POSIX
Classifier: License :: OSI Approved :: MIT License
Classifier: Development Status :: 3 - Alpha
Classifier: Programming Language :: Python
Classifier: Programming Language :: Python :: 3
Classifier: Programming Language :: Python :: 3.4
Classifier: Programming Language :: Python :: 3.5
Classifier: Operating System :: POSIX
Classifier: Environment :: Web Environment
Classifier: Intended Audience :: Developers
Classifier: Topic :: Software Development
Classifier: Topic :: Software Development :: Libraries
